{
  "_markup_path": "markup/sn/sn07/sn7.19.html",
  "_alt_strings": [
    "pi/sn/sn07/sn7.19.json"
  ],
  "sn7.19:1.1": "Linked Discourses 7",
  "sn7.19:2.1": "2 Lay Followers",
  "sn7.19:3.1": "19 The Brahmin Who Provided for His Mother",
  "sn7.19:4.1": "At Sāvatthī.",
  "sn7.19:4.2": "Then a brahmin who provided for his mother went up to the Buddha, ",
  "sn7.19:4.3": "and exchanged greetings with him.",
  "sn7.19:4.4": "When the greetings and polite conversation were over, he sat down to one side, ",
  "sn7.19:4.5": "and said to the Buddha:",
  "sn7.19:4.6": "“Master Gotama, I seek for alms by legitimate means, which I use to provide for my mother and father.",
  "sn7.19:4.7": "In doing so, am I doing my duty?”",
  "sn7.19:4.8": "“Indeed, brahmin, in so doing you are doing your duty.",
  "sn7.19:4.9": "Whoever seeks for alms by legitimate means, and uses them to provide for their mother and father makes much merit.”",
  "sn7.19:5.1": "“A mortal provides for their mother",
  "sn7.19:5.2": "and father by legitimate means;",
  "sn7.19:5.3": "because they look after",
  "sn7.19:5.4": "their parents like this,",
  "sn7.19:5.5": "they’re praised in this life by the astute,",
  "sn7.19:5.6": "and they depart to rejoice in heaven.”",
  "sn7.19:6.1": "When he said this, the brahmin who provided for his mother said to the Buddha:",
  "sn7.19:6.2": "“Excellent, Master Gotama! Excellent! …",
  "sn7.19:6.3": "From this day forth, may Master Gotama remember me as a lay follower who has gone for refuge for life.”"
}