{
  "_markup_path": "markup/an/an04/an4.214.html",
  "_alt_strings": [
    "pi/an/an04/an4.214.json"
  ],
  "an4.214:1.1": "Numbered Discourses 4",
  "an4.214:2.1": "22 Assembly",
  "an4.214:3.1": "214 Killing Living Beings",
  "an4.214:4.1": "“Someone with four qualities is cast down to hell. … They kill living creatures, steal, commit sexual misconduct, and lie. … Someone with four qualities is raised up to heaven. … They don’t kill living creatures, steal, commit sexual misconduct, or lie. …”"
}