{
  "_markup_path": "markup/an/an04/an4.020.html",
  "_alt_strings": [
    "pi/an/an04/an4.020.json"
  ],
  "an4.20:1.1": "Numbered Discourses 4",
  "an4.20:2.1": "2 Walking",
  "an4.20:3.1": "20 A Meal-allocator",
  "an4.20:4.1": "“Mendicants, a meal-allocator who has four qualities is cast down to hell.",
  "an4.20:4.2": "What four?",
  "an4.20:4.3": "They make decisions prejudiced by favoritism, hostility, stupidity, and cowardice.",
  "an4.20:4.4": "A meal-allocator who has these four qualities is cast down to hell.",
  "an4.20:5.1": "A meal-allocator who has four qualities is raised up to heaven.",
  "an4.20:5.2": "What four?",
  "an4.20:5.3": "They make decisions unprejudiced by favoritism, hostility, stupidity, and cowardice.",
  "an4.20:5.4": "A meal-allocator who has these four qualities is raised up to heaven.”",
  "an4.20:6.1": "“All those people with uncontrolled sensuality,",
  "an4.20:6.2": "unprincipled, with no respect for principle,",
  "an4.20:6.3": "led astray by favoritism, hatred, stupidity, or cowardice,",
  "an4.20:6.4": "are called ‘an assembly of the dregs’:",
  "an4.20:7.1": "that’s what was said by the ascetic who knows.",
  "an4.20:7.2": "And so those good, praiseworthy people,",
  "an4.20:7.3": "standing on principle, doing nothing wrong,",
  "an4.20:7.4": "not led astray by favoritism, hatred, stupidity, or cowardice,",
  "an4.20:7.5": "are called ‘an assembly of the cream’:",
  "an4.20:7.6": "that’s what was said by the ascetic who knows.”"
}