{
  "_markup_path": "markup/an/an04/an4.262.html",
  "_alt_strings": [
    "pi/an/an04/an4.262.json"
  ],
  "an4.262:1.1": "Numbered Discourses 4",
  "an4.262:2.1": "26 Insight",
  "an4.262:3.1": "262 Wilderness",
  "an4.262:4.1": "“Mendicants, when a mendicant has four qualities they’re not ready to frequent remote wilderness and jungle lodgings.",
  "an4.262:4.2": "What four?",
  "an4.262:4.3": "They have sensual, malicious, and cruel thoughts; or they’re witless, dull, and stupid. ",
  "an4.262:4.4": "When a mendicant has these four qualities they’re not ready to frequent remote wilderness and jungle lodgings.",
  "an4.262:5.1": "When a mendicant has four qualities they’re ready to frequent remote wilderness and jungle lodgings.",
  "an4.262:5.2": "What four?",
  "an4.262:5.3": "They have thoughts of renunciation, love, and kindness; and they’re wise, bright, and intelligent.",
  "an4.262:5.4": "When a mendicant has these four qualities they’re ready to frequent remote wilderness and jungle lodgings.”"
}