{
  "_markup_path": "markup/sn/sn56/sn56.120-122.html",
  "_alt_strings": [
    "en/sujato/sn/sn56/sn56.120-122.json"
  ],
  "sn56.120-122:1.1": "Saṃyutta Nikāya 56",
  "sn56.120-122:2.1": "11. Pañcagatipeyyālavagga",
  "sn56.120-122:3.1": "<span class=\\\"var\\\" title=\\\"tiracchānacutisuttaṃ (bj)\\\" id=\\\"note643\\\">120–​122. Tiracchānamanussanirayādisutta</span>",
  "sn56.120-122:4.1": "… “Evameva kho, bhikkhave, appakā te sattā ye tiracchānayoniyā cutā manussesu paccājāyanti;",
  "sn56.120-122:4.2": "atha kho eteva bahutarā sattā ye tiracchānayoniyā cutā niraye paccājāyanti … pe …",
  "sn56.120-122:4.3": "tiracchānayoniyā paccājāyanti … pe …",
  "sn56.120-122:4.4": "pettivisaye paccājāyanti … pe ….",
  "sn56.120-122:5.1": "Ekavīsatimaṃ."
}