{
  "_markup_path": "markup/sn/sn56/sn56.090.html",
  "_alt_strings": [
    "en/sujato/sn/sn56/sn56.090.json"
  ],
  "sn56.90:1.1": "Saṃyutta Nikāya 56",
  "sn56.90:2.1": "9. Tatiyaāmakadhaññapeyyālavagga",
  "sn56.90:3.1": "<span class=\\\"var\\\" title=\\\"vaḷavāsuttaṃ (bj) | hatthino (pts1)\\\" id=\\\"note627\\\">90. Hatthigavassasutta</span>",
  "sn56.90:4.1": "… “Evameva kho, bhikkhave, appakā te sattā ye <span class=\\\"var\\\" title=\\\"hatthigavassavaḷavāpaṭiggahaṇā (bj, s1-3, km, pts1, mr)\\\" id=\\\"note628\\\">hatthigavassavaḷavapaṭiggahaṇā</span> paṭiviratā;",
  "sn56.90:4.2": "atha kho eteva bahutarā sattā ye hatthigavassavaḷavapaṭiggahaṇā appaṭiviratā … pe ….",
  "sn56.90:5.1": "Dasamaṃ.",
  "sn56.90:6.1": "Tatiyaāmakadhaññapeyyālavaggo navamo.",
  "sn56.90:7.1": "Naccaṃ sayanaṃ rajataṃ,",
  "sn56.90:7.2": "dhaññaṃ maṃsaṃ kumārikā;",
  "sn56.90:7.3": "Dāsī ajeḷakañceva,",
  "sn56.90:7.4": "kukkuṭasūkarahatthīti."
}