{
  "_markup_path": "markup/an/an03/an3.103.html",
  "_alt_strings": [
    "pi/an/an03/an3.103.json"
  ],
  "an3.103:1.1": "Numbered Discourses 3",
  "an3.103:2.1": "11 Awakening",
  "an3.103:3.1": "103 Before Awakening",
  "an3.103:4.1": "“Mendicants, before my awakening—when I was unawakened but intent on awakening—I thought:",
  "an3.103:4.2": "‘What’s the gratification in the world? What’s the drawback? What’s the escape?’",
  "an3.103:4.3": "Then it occurred to me: ",
  "an3.103:4.4": "‘The pleasure and happiness that arise from the world: this is its gratification.",
  "an3.103:4.5": "That the world is impermanent, suffering, and perishable: this is its drawback.",
  "an3.103:4.6": "Removing and giving up desire and greed for the world: this is its escape.",
  "an3.103:4.7": "As long as I didn’t truly understand the world’s gratification, drawback, and escape in this way for what they are, I didn’t announce my supreme perfect awakening in this world with its gods, Māras, and Brahmās, this population with its ascetics and brahmins, its gods and humans.",
  "an3.103:4.8": "But when I did truly understand the world’s gratification, drawback, and escape in this way for what they are, I announced my supreme perfect awakening in this world with its gods, Māras, and Brahmās, this population with its ascetics and brahmins, its gods and humans.",
  "an3.103:4.9": "Knowledge and vision arose in me:",
  "an3.103:4.10": "‘My freedom is unshakeable; this is my final birth; now there are no more future lives.’”"
}