{
  "_markup_path": "markup/an/an03/an3.006.html",
  "_alt_strings": [
    "pi/an/an03/an3.006.json"
  ],
  "an3.6:1.1": "Numbered Discourses 3",
  "an3.6:2.1": "1 Fools",
  "an3.6:3.1": "6 Unwholesome",
  "an3.6:4.1": "“A fool is known by three things.",
  "an3.6:4.2": "What three?",
  "an3.6:4.3": "Unwholesome deeds by way of body, speech, and mind.",
  "an3.6:4.4": "These are the three things by which a fool is known.",
  "an3.6:5.1": "An astute person is known by three things.",
  "an3.6:5.2": "What three?",
  "an3.6:5.3": "Wholesome deeds by way of body, speech, and mind.",
  "an3.6:5.4": "These are the three things by which an astute person is known.",
  "an3.6:5.5": "So you should train …”"
}