{
  "_markup_path": "markup/an/an02/an2.163-179.html",
  "_alt_strings": [
    "pi/an/an02/an2.163-179.json"
  ],
  "an2.163-179:1.1": "Numbered Discourses 2",
  "an2.163-179:2.1": "15 Attainment",
  "an2.163-179:3.1": "163",
  "an2.163-179:4.1": "“There are these two things.",
  "an2.163-179:4.2": "What two?",
  "an2.163-179:4.3": "Skill in meditative attainments and skill in emerging from those attainments.",
  "an2.163-179:4.4": "These are the two things.”",
  "an2.163-179:5.1": "164",
  "an2.163-179:6.1": "“There are these two things.",
  "an2.163-179:6.2": "What two?",
  "an2.163-179:6.3": "Integrity and gentleness.",
  "an2.163-179:6.4": "These are the two things.”",
  "an2.163-179:7.1": "165",
  "an2.163-179:8.1": "“There are these two things.",
  "an2.163-179:8.2": "What two?",
  "an2.163-179:8.3": "Acceptance and gentleness.",
  "an2.163-179:8.4": "These are the two things.”",
  "an2.163-179:9.1": "166",
  "an2.163-179:10.1": "“There are these two things.",
  "an2.163-179:10.2": "What two?",
  "an2.163-179:10.3": "Friendliness and hospitality.",
  "an2.163-179:10.4": "These are the two things.”",
  "an2.163-179:11.1": "167",
  "an2.163-179:12.1": "“There are these two things.",
  "an2.163-179:12.2": "What two?",
  "an2.163-179:12.3": "Harmlessness and purity.",
  "an2.163-179:12.4": "These are the two things.”",
  "an2.163-179:13.1": "168",
  "an2.163-179:14.1": "“There are these two things.",
  "an2.163-179:14.2": "What two?",
  "an2.163-179:14.3": "Not guarding the sense doors and eating too much.",
  "an2.163-179:14.4": "These are the two things.”",
  "an2.163-179:15.1": "169",
  "an2.163-179:16.1": "“There are these two things.",
  "an2.163-179:16.2": "What two?",
  "an2.163-179:16.3": "Guarding the sense doors and moderation in eating.",
  "an2.163-179:16.4": "These are the two things.”",
  "an2.163-179:17.1": "170",
  "an2.163-179:18.1": "“There are these two things.",
  "an2.163-179:18.2": "What two?",
  "an2.163-179:18.3": "The power of reflection, and the power of development.",
  "an2.163-179:18.4": "These are the two things.”",
  "an2.163-179:19.1": "171",
  "an2.163-179:20.1": "“There are, mendicants, these two things.",
  "an2.163-179:20.2": "What two?",
  "an2.163-179:20.3": "The power of mindfulness and the power of samādhi.",
  "an2.163-179:20.4": "These are the two things.”",
  "an2.163-179:21.1": "172",
  "an2.163-179:22.1": "“There are these two things.",
  "an2.163-179:22.2": "What two?",
  "an2.163-179:22.3": "Serenity and discernment.",
  "an2.163-179:22.4": "These are the two things.”",
  "an2.163-179:23.1": "173",
  "an2.163-179:24.1": "“There are these two things.",
  "an2.163-179:24.2": "What two?",
  "an2.163-179:24.3": "Failure in ethical conduct and failure in view.",
  "an2.163-179:24.4": "These are the two things.”",
  "an2.163-179:25.1": "174",
  "an2.163-179:26.1": "“There are these two things.",
  "an2.163-179:26.2": "What two?",
  "an2.163-179:26.3": "Accomplishment in ethical conduct and accomplishment in view.",
  "an2.163-179:26.4": "These are the two things.”",
  "an2.163-179:27.1": "175",
  "an2.163-179:28.1": "“There are these two things.",
  "an2.163-179:28.2": "What two?",
  "an2.163-179:28.3": "Purification of ethics and purification of view.",
  "an2.163-179:28.4": "These are the two things.”",
  "an2.163-179:29.1": "176",
  "an2.163-179:30.1": "“There are these two things.",
  "an2.163-179:30.2": "What two?",
  "an2.163-179:30.3": "Purification of view and making an effort in line with that view.",
  "an2.163-179:30.4": "These are the two things.”",
  "an2.163-179:31.1": "177",
  "an2.163-179:32.1": "“There are these two things.",
  "an2.163-179:32.2": "What two?",
  "an2.163-179:32.3": "To never be content with wholesome qualities, and to never stop trying.",
  "an2.163-179:32.4": "These are the two things.”",
  "an2.163-179:33.1": "178",
  "an2.163-179:34.1": "“There are these two things.",
  "an2.163-179:34.2": "What two?",
  "an2.163-179:34.3": "Being confused and lacking situational awareness.",
  "an2.163-179:34.4": "These are the two things.”",
  "an2.163-179:35.1": "179",
  "an2.163-179:36.1": "“There are these two things.",
  "an2.163-179:36.2": "What two?",
  "an2.163-179:36.3": "Mindfulness and situational awareness.",
  "an2.163-179:36.4": "These are the two things.”"
}