{
  "_markup_path": "markup/sn/sn12/sn12.60.html",
  "_alt_strings": [
    "en/sujato/sn/sn12/sn12.60.json"
  ],
  "sn12.60:1.1": "Saṃyutta Nikāya 12",
  "sn12.60:2.1": "6. Dukkhavagga",
  "sn12.60:3.1": "<span class=\\\"var\\\" title=\\\"nidāna (paṭiccasamuppāda) suttaṃ (bj)\\\" id=\\\"note83\\\">60. Nidānasutta</span>",
  "sn12.60:4.1": "Ekaṃ samayaṃ bhagavā kurūsu viharati kammāsadhammaṃ nāma kurūnaṃ nigamo.",
  "sn12.60:4.2": "Atha kho āyasmā ānando yena bhagavā tenupasaṅkami;",
  "sn12.60:4.3": "upasaṅkamitvā bhagavantaṃ abhivādetvā ekamantaṃ nisīdi.",
  "sn12.60:4.4": "Ekamantaṃ nisinno kho āyasmā ānando bhagavantaṃ etadavoca:",
  "sn12.60:4.5": "“acchariyaṃ, bhante, abbhutaṃ, bhante.",
  "sn12.60:4.6": "Yāva gambhīro cāyaṃ, bhante, paṭiccasamuppādo gambhīrāvabhāso ca, atha ca pana me uttānakuttānako viya khāyatī”ti.",
  "sn12.60:5.1": "“Mā <span class=\\\"var\\\" title=\\\"mā hevaṃ ānanda avaca mā hevaṃ ānanda avaca (^dn15#1 [Mahānidānasutta/1. Paṭiccasamuppāda] mahānidānasutte)\\\" id=\\\"note84\\\">hevaṃ, ānanda, mā hevaṃ, ānanda</span>.",
  "sn12.60:5.2": "Gambhīro cāyaṃ, ānanda, paṭiccasamuppādo gambhīrāvabhāso ca.",
  "sn12.60:5.3": "Etassa, ānanda, dhammassa ananubodhā appaṭivedhā evamayaṃ pajā tantākulakajātā <span class=\\\"var\\\" title=\\\"guḷāguṇṭhikajātā (bj) | guḷīguṇṭhikajātā (s1-3, km) | guḷigandhikajātā (pts1-2)\\\" id=\\\"note85\\\">kulagaṇṭhikajātā</span> <span class=\\\"var\\\" title=\\\"muñjababbajabhūtā (bj)\\\" id=\\\"note86\\\">muñjapabbajabhūtā</span> apāyaṃ duggatiṃ vinipātaṃ saṃsāraṃ nātivattati.",
  "sn12.60:6.1": "Upādāniyesu, ānanda, dhammesu assādānupassino viharato taṇhā pavaḍḍhati.",
  "sn12.60:6.2": "Taṇhāpaccayā upādānaṃ;",
  "sn12.60:6.3": "upādānapaccayā bhavo;",
  "sn12.60:6.4": "bhavapaccayā jāti;",
  "sn12.60:6.5": "jātipaccayā jarāmaraṇaṃ sokaparidevadukkhadomanassupāyāsā sambhavanti.",
  "sn12.60:6.6": "Evametassa kevalassa dukkhakkhandhassa samudayo hoti.",
  "sn12.60:7.1": "Seyyathāpi, ānanda, mahārukkho.",
  "sn12.60:7.2": "Tassa yāni ceva mūlāni adhogamāni, yāni ca tiriyaṅgamāni, sabbāni tāni uddhaṃ ojaṃ abhiharanti.",
  "sn12.60:7.3": "Evañhi so, ānanda, mahārukkho tadāhāro tadupādāno ciraṃ dīghamaddhānaṃ tiṭṭheyya.",
  "sn12.60:7.4": "Evameva kho, ānanda, upādāniyesu dhammesu assādānupassino viharato taṇhā pavaḍḍhati.",
  "sn12.60:7.5": "Taṇhāpaccayā upādānaṃ;",
  "sn12.60:7.6": "upādānapaccayā bhavo … pe …",
  "sn12.60:7.7": "evametassa kevalassa dukkhakkhandhassa samudayo hoti.",
  "sn12.60:8.1": "Upādāniyesu, ānanda, dhammesu ādīnavānupassino viharato taṇhā nirujjhati.",
  "sn12.60:8.2": "Taṇhānirodhā upādānanirodho;",
  "sn12.60:8.3": "upādānanirodhā bhavanirodho … pe …",
  "sn12.60:8.4": "evametassa kevalassa dukkhakkhandhassa nirodho hoti.",
  "sn12.60:9.1": "Seyyathāpi, ānanda, mahārukkho.",
  "sn12.60:9.2": "Atha puriso āgaccheyya kuddālapiṭakaṃ ādāya.",
  "sn12.60:9.3": "So taṃ rukkhaṃ mūle chindeyya, mūle chetvā palikhaṇeyya, palikhaṇitvā mūlāni uddhareyya antamaso usīranāḷimattānipi.",
  "sn12.60:9.4": "So taṃ rukkhaṃ khaṇḍākhaṇḍikaṃ chindeyya.",
  "sn12.60:9.5": "Khaṇḍākhaṇḍikaṃ chinditvā phāleyya;",
  "sn12.60:9.6": "phāletvā sakalikaṃ sakalikaṃ kareyya, sakalikaṃ sakalikaṃ karitvā vātātape visoseyya, vātātape visosetvā agginā ḍaheyya, agginā ḍahetvā masiṃ kareyya, masiṃ karitvā mahāvāte vā ophuṇeyya, nadiyā vā sīghasotāya pavāheyya.",
  "sn12.60:9.7": "Evañhi so, ānanda, mahārukkho ucchinnamūlo assa tālāvatthukato anabhāvaṅkato āyatiṃ anuppādadhammo.",
  "sn12.60:9.8": "Evameva kho, ānanda, upādāniyesu dhammesu ādīnavānupassino viharato taṇhā nirujjhati.",
  "sn12.60:9.9": "Taṇhānirodhā upādānanirodho;",
  "sn12.60:9.10": "upādānanirodhā bhavanirodho;",
  "sn12.60:9.11": "bhavanirodhā jātinirodho;",
  "sn12.60:9.12": "jātinirodhā jarāmaraṇaṃ sokaparidevadukkhadomanassupāyāsā nirujjhanti.",
  "sn12.60:9.13": "Evametassa kevalassa dukkhakkhandhassa nirodho hotī”ti.",
  "sn12.60:10.1": "Dasamaṃ.",
  "sn12.60:11.1": "Dukkhavaggo chaṭṭho.",
  "sn12.60:12.1": "Parivīmaṃsanupādānaṃ,",
  "sn12.60:12.2": "dve ca saṃyojanāni ca;",
  "sn12.60:12.3": "Mahārukkhena dve vuttā,",
  "sn12.60:12.4": "taruṇena ca sattamaṃ;",
  "sn12.60:12.5": "Nāmarūpañca viññāṇaṃ,",
  "sn12.60:12.6": "nidānena ca te dasāti."
}