{
  "_markup_path": "markup/sn/sn35/sn35.145.html",
  "_alt_strings": [
    "pi/sn/sn35/sn35.145.json"
  ],
  "sn35.145:1.1": "Linked Discourses 35 ",
  "sn35.145:2.1": "14 At Devadaha ",
  "sn35.145:3.1": "145 Exterior and Cause Are Not-Self",
  "sn35.145:4.1": "“Mendicants, sights are not-self. ",
  "sn35.145:4.2": "The cause and condition that gives rise to sights is also not-self.",
  "sn35.145:4.3": "Since sights are produced by what is not-self, how could they be self?",
  "sn35.145:4.4": "Sounds …",
  "sn35.145:4.5": "smells …",
  "sn35.145:4.6": "tastes …",
  "sn35.145:4.7": "touches …",
  "sn35.145:4.8": "phenomena are not-self.",
  "sn35.145:4.9": "The cause and condition that gives rise to phenomena is also not-self.",
  "sn35.145:4.10": "Since phenomena are produced by what is not-self, how could they be self?",
  "sn35.145:4.11": "Seeing this …",
  "sn35.145:4.19": "They understand: ‘Rebirth is ended, the spiritual life has been lived, what had to be done has been done, there is no return to any state of existence.’”"
}