{
  "_markup_path": "markup/an/an03/an3.183-352.html",
  "_alt_strings": [
    "en/sujato/an/an03/an3.183-352.json"
  ],
  "an3.183-352:1.1": "Aṅguttara Nikāya 3",
  "an3.183-352:2.1": "18. Rāgapeyyāla",
  "an3.183-352:3.1": "183–​352",
  "an3.183-352:4.1": "“Rāgassa, bhikkhave, abhiññāya tayo dhammā bhāvetabbā.",
  "an3.183-352:4.2": "Katame tayo?",
  "an3.183-352:4.3": "Suññato samādhi, animitto samādhi, appaṇihito samādhi—",
  "an3.183-352:4.4": "rāgassa, bhikkhave, abhiññāya ime tayo dhammā bhāvetabbā. <span class=\"brnum\">(1)</span> <span class=\"var\" title=\"(rāgassa bhikkhave abhiññāya tayo dhammā bhāvetabbā. katame tayo? savitakkasavicāro samādhi, avitakkavicāramatto samādhi, avitakkaavicāro samādhi. rāgassa bhikkhave abhiññāya ime tayo dhammā bhāvetabbā.) etthantare pāṭho katthaci dissati, aṭṭhakathāyaṃ\" id=\"note462\">()</span>",
  "an3.183-352:5.1": "Rāgassa, bhikkhave, pariññāya … pe …",
  "an3.183-352:5.2": "parikkhayāya …",
  "an3.183-352:5.3": "pahānāya …",
  "an3.183-352:5.4": "khayāya …",
  "an3.183-352:5.5": "vayāya …",
  "an3.183-352:5.6": "virāgāya …",
  "an3.183-352:5.7": "nirodhāya …",
  "an3.183-352:5.8": "cāgāya …",
  "an3.183-352:5.9": "paṭinissaggāya ime tayo dhammā bhāvetabbā.",
  "an3.183-352:6.1": "Dosassa …",
  "an3.183-352:6.2": "mohassa …",
  "an3.183-352:6.3": "kodhassa …",
  "an3.183-352:6.4": "upanāhassa …",
  "an3.183-352:6.5": "makkhassa …",
  "an3.183-352:6.6": "paḷāsassa …",
  "an3.183-352:6.7": "issāya …",
  "an3.183-352:6.8": "macchariyassa …",
  "an3.183-352:6.9": "māyāya …",
  "an3.183-352:6.10": "sāṭheyyassa …",
  "an3.183-352:6.11": "thambhassa …",
  "an3.183-352:6.12": "sārambhassa …",
  "an3.183-352:6.13": "mānassa …",
  "an3.183-352:6.14": "atimānassa …",
  "an3.183-352:6.15": "madassa …",
  "an3.183-352:6.16": "pamādassa …",
  "an3.183-352:6.17": "abhiññāya …",
  "an3.183-352:6.18": "pariññāya …",
  "an3.183-352:6.19": "parikkhayāya …",
  "an3.183-352:6.20": "pahānāya …",
  "an3.183-352:6.21": "khayāya …",
  "an3.183-352:6.22": "vayāya …",
  "an3.183-352:6.23": "virāgāya …",
  "an3.183-352:6.24": "nirodhāya …",
  "an3.183-352:6.25": "cāgāya …",
  "an3.183-352:6.26": "paṭinissaggāya ime tayo dhammā bhāvetabbā”ti.",
  "an3.183-352:7.1": "<span class=\"var\" title=\" etthantare pāṭho syā1-3, kaṃ, ka-ma potthakesu na\" id=\"note463\">Idamavoca bhagavā.",
  "an3.183-352:7.2": "Attamanā te bhikkhū bhagavato bhāsitaṃ abhinandunti</span>.",
  "an3.183-352:8.1": "Rāgapeyyālaṃ niṭṭhitaṃ.",
  "an3.183-352:9.1": "<span class=\"cross\" title=\"imā uddānagāthāyo bj, s1-3, km, pts1 potthakesu na\" id=\"note465\">*</span> <a class=\"sc\" id=\"5\"></a>Rāgaṃ dosañca mohañca,",
  "an3.183-352:9.2": "kodhūpanāhapañcamaṃ;",
  "an3.183-352:9.3": "Makkhapaḷāsaissā ca,",
  "an3.183-352:9.4": "maccharimāyāsāṭheyyā.",
  "an3.183-352:10.1": "Thambhasārambhamānañca,",
  "an3.183-352:10.2": "atimānamadassa ca;",
  "an3.183-352:10.3": "Pamādā sattarasa vuttā,",
  "an3.183-352:10.4": "rāgapeyyālanissitā.",
  "an3.183-352:11.1": "Ete opammayuttena,",
  "an3.183-352:11.2": "āpādena abhiññāya;",
  "an3.183-352:11.3": "Pariññāya parikkhayā,",
  "an3.183-352:11.4": "pahānakkhayabbayena;",
  "an3.183-352:11.5": "Virāganirodhacāgaṃ,",
  "an3.183-352:11.6": "paṭinissagge ime dasa.",
  "an3.183-352:12.1": "Suññato animitto ca,",
  "an3.183-352:12.2": "appaṇihito ca tayo;",
  "an3.183-352:12.3": "Samādhimūlakā peyyā—​",
  "an3.183-352:12.4": "lesupi vavatthitā cāti.",
  "an3.183-352:13.1": "Tatiyo paṇṇāsako niṭṭhito.",
  "an3.183-352:14.1": "Tikanipātapāḷi niṭṭhitā."
}