{
  "_markup_path": "markup/an/an03/an3.046.html",
  "_alt_strings": [
    "en/sujato/an/an03/an3.046.json"
  ],
  "an3.46:1.1": "Aṅguttara Nikāya 3",
  "an3.46:2.1": "5. Cūḷavagga",
  "an3.46:3.1": "46. Sīlavantasutta",
  "an3.46:4.1": "“Yaṃ, bhikkhave, sīlavanto pabbajitā gāmaṃ vā nigamaṃ vā upanissāya viharanti.",
  "an3.46:4.2": "Tattha manussā tīhi ṭhānehi bahuṃ puññaṃ pasavanti.",
  "an3.46:4.3": "Katamehi tīhi?",
  "an3.46:4.4": "Kāyena, vācāya, manasā.",
  "an3.46:4.5": "Yaṃ, bhikkhave, sīlavanto pabbajitā gāmaṃ vā nigamaṃ vā upanissāya viharanti.",
  "an3.46:4.6": "Tattha manussā imehi tīhi ṭhānehi bahuṃ puññaṃ pasavantī”ti.",
  "an3.46:5.1": "Chaṭṭhaṃ."
}