{
  "_markup_path": "markup/sn/sn36/sn36.24.html",
  "_alt_strings": [
    "en/sujato/sn/sn36/sn36.24.json"
  ],
  "sn36.24:1.1": "Saṃyutta Nikāya 36",
  "sn36.24:2.1": "3. Aṭṭhasatapariyāyavagga",
  "sn36.24:3.1": "<span class=\\\"var\\\" title=\\\"pubbesuttaṃ (bj) | pubbeñāṇaṃ (pts1)\\\" id=\\\"note385\\\">24. Pubbasutta</span>",
  "sn36.24:4.1": "“Pubbeva me, bhikkhave, sambodhā anabhisambuddhassa bodhisattasseva sato etadahosi:",
  "sn36.24:4.2": "‘katamā nu kho vedanā, katamo vedanāsamudayo, katamā vedanāsamudayagāminī paṭipadā, katamo vedanānirodho, katamā vedanānirodhagāminī paṭipadā?",
  "sn36.24:4.3": "Ko vedanāya assādo, ko ādīnavo, kiṃ nissaraṇan’ti?",
  "sn36.24:4.4": "Tassa mayhaṃ, bhikkhave, etadahosi:",
  "sn36.24:4.5": "‘tisso imā vedanā—",
  "sn36.24:4.6": "sukhā vedanā, dukkhā vedanā, adukkhamasukhā vedanā.",
  "sn36.24:4.7": "Imā vuccanti vedanā.",
  "sn36.24:4.8": "Phassasamudayā vedanāsamudayo.",
  "sn36.24:4.9": "Taṇhā vedanāsamudayagāminī paṭipadā … pe …",
  "sn36.24:4.10": "yo vedanāya chandarāgavinayo chandarāgappahānaṃ.",
  "sn36.24:4.11": "Idaṃ vedanāya nissaraṇan’”ti.",
  "sn36.24:5.1": "Catutthaṃ."
}