{
  "_markup_path": "markup/sn/sn36/sn36.13.html",
  "_alt_strings": [
    "en/sujato/sn/sn36/sn36.13.json"
  ],
  "sn36.13:1.1": "Saṃyutta Nikāya 36",
  "sn36.13:2.1": "2. Rahogatavagga",
  "sn36.13:3.1": "13. Dutiyaākāsasutta",
  "sn36.13:4.1": "“Seyyathāpi, bhikkhave, ākāse vividhā vātā vāyanti.",
  "sn36.13:4.2": "Puratthimāpi vātā vāyanti … pe …",
  "sn36.13:4.3": "adhimattāpi vātā vāyanti.",
  "sn36.13:4.4": "Evameva kho, bhikkhave, imasmiṃ kāyasmiṃ vividhā vedanā uppajjanti, sukhāpi vedanā uppajjati, dukkhāpi vedanā uppajjati, adukkhamasukhāpi vedanā uppajjatī”ti.",
  "sn36.13:5.1": "Tatiyaṃ."
}