{
  "_markup_path": "markup/sn/sn48/sn48.048.html",
  "_alt_strings": [
    "en/sujato/sn/sn48/sn48.048.json"
  ],
  "sn48.48:1.1": "Saṃyutta Nikāya 48",
  "sn48.48:2.1": "5. Jarāvagga",
  "sn48.48:3.1": "48. Catutthapubbārāmasutta",
  "sn48.48:4.1": "Taṃyeva nidānaṃ.",
  "sn48.48:4.2": "“Katinaṃ nu kho, bhikkhave, indriyānaṃ bhāvitattā bahulīkatattā khīṇāsavo bhikkhu aññaṃ byākaroti:",
  "sn48.48:4.3": "‘khīṇā jāti, vusitaṃ brahmacariyaṃ, kataṃ karaṇīyaṃ, nāparaṃ itthattāyā’ti pajānāmī”ti?",
  "sn48.48:5.1": "“Bhagavaṃmūlakā no, bhante, dhammā … pe …",
  "sn48.48:5.2": "“pañcannaṃ kho, bhikkhave, indriyānaṃ bhāvitattā bahulīkatattā khīṇāsavo bhikkhu aññaṃ byākaroti:",
  "sn48.48:5.3": "‘khīṇā jāti, vusitaṃ brahmacariyaṃ, kataṃ karaṇīyaṃ, nāparaṃ itthattāyā’ti pajānāmīti.",
  "sn48.48:5.4": "Katamesaṃ pañcannaṃ?",
  "sn48.48:5.5": "Saddhindriyassa, vīriyindriyassa, satindriyassa, samādhindriyassa, paññindriyassa—",
  "sn48.48:5.6": "imesaṃ kho, bhikkhave, pañcannaṃ indriyānaṃ bhāvitattā bahulīkatattā khīṇāsavo bhikkhu aññaṃ byākaroti:",
  "sn48.48:5.7": "‘khīṇā jāti, vusitaṃ brahmacariyaṃ, kataṃ karaṇīyaṃ, nāparaṃ itthattāyā’ti pajānāmī”ti.",
  "sn48.48:6.1": "Aṭṭhamaṃ."
}