{
  "_markup_path": "markup/sn/sn22/sn22.150.html",
  "_alt_strings": [
    "en/sujato/sn/sn22/sn22.150.json"
  ],
  "sn22.150:1.1": "Saṃyutta Nikāya 22",
  "sn22.150:2.1": "15. Diṭṭhivagga",
  "sn22.150:3.1": "<span class=\\\"var\\\" title=\\\"ajjhattikaṃ (pts1)\\\" id=\\\"note213\\\">150. Ajjhattasutta</span>",
  "sn22.150:4.1": "Sāvatthinidānaṃ.",
  "sn22.150:4.2": "“Kismiṃ nu kho, bhikkhave, sati, kiṃ upādāya uppajjati ajjhattaṃ sukhadukkhan”ti?",
  "sn22.150:4.3": "Bhagavaṃmūlakā no, bhante, dhammā … pe …",
  "sn22.150:4.4": "“rūpe kho, bhikkhave, sati rūpaṃ upādāya uppajjati ajjhattaṃ sukhadukkhaṃ.",
  "sn22.150:4.5": "Vedanāya sati … pe …",
  "sn22.150:4.6": "saññāya sati …",
  "sn22.150:4.7": "saṅkhāresu sati …",
  "sn22.150:4.8": "viññāṇe sati viññāṇaṃ upādāya uppajjati ajjhattaṃ sukhadukkhaṃ.",
  "sn22.150:4.9": "Taṃ kiṃ maññatha, bhikkhave, rūpaṃ niccaṃ vā aniccaṃ vā”ti?",
  "sn22.150:4.10": "“Aniccaṃ, bhante”.",
  "sn22.150:4.11": "“Yaṃ panāniccaṃ dukkhaṃ vā taṃ sukhaṃ vā”ti?",
  "sn22.150:4.12": "“Dukkhaṃ, bhante”.",
  "sn22.150:4.13": "“Yaṃ panāniccaṃ dukkhaṃ vipariṇāmadhammaṃ, api nu taṃ anupādāya uppajjeyya ajjhattaṃ sukhadukkhan”ti?",
  "sn22.150:4.14": "“No hetaṃ, bhante”.",
  "sn22.150:4.15": "“Vedanā … pe …",
  "sn22.150:4.16": "saññā …",
  "sn22.150:4.17": "saṅkhārā …",
  "sn22.150:4.18": "viññāṇaṃ niccaṃ vā aniccaṃ vā”ti?",
  "sn22.150:4.19": "“Aniccaṃ, bhante”.",
  "sn22.150:4.20": "“Yaṃ panāniccaṃ dukkhaṃ vā taṃ sukhaṃ vā”ti?",
  "sn22.150:4.21": "“Dukkhaṃ, bhante”.",
  "sn22.150:4.22": "“Yaṃ panāniccaṃ dukkhaṃ vipariṇāmadhammaṃ, api nu taṃ anupādāya uppajjeyya ajjhattaṃ sukhadukkhan”ti?",
  "sn22.150:4.23": "“No hetaṃ, bhante”.",
  "sn22.150:4.24": "“Evaṃ passaṃ … pe …",
  "sn22.150:4.25": "nāparaṃ itthattāyāti pajānātī”ti.",
  "sn22.150:5.1": "Paṭhamaṃ."
}