{
  "_markup_path": "markup/an/an11/an11.022-29.html",
  "_alt_strings": [
    "pi/an/an11/an11.022-29.json"
  ],
  "an11.22-29:1.1": "Numbered Discourses 11 ",
  "an11.22-29:2.1": "3 Similarity",
  "an11.22-29:3.1": "22–​29",
  "an11.22-29:4.1": "“Mendicants, a cowherd with eleven factors can’t maintain and expand a herd of cattle.",
  "an11.22-29:4.2": "What eleven?",
  "an11.22-29:4.3": "It’s when a cowherd doesn’t know form, is unskilled in characteristics, doesn’t pick out flies’ eggs, doesn’t dress wounds, doesn’t smoke out pests, doesn’t know the ford, doesn’t know when they’re satisfied, doesn’t know the trail, is not skilled in pastures, milks dry, and doesn’t show extra respect to the bulls who are fathers and leaders of the herd. ",
  "an11.22-29:4.4": "A cowherd with these eleven factors can’t maintain and expand a herd of cattle.",
  "an11.22-29:5.1": "In the same way, a mendicant with eleven qualities can’t meditate observing impermanence in the eye …",
  "an11.22-29:5.2": "suffering …",
  "an11.22-29:5.3": "not-self …",
  "an11.22-29:5.4": "ending …",
  "an11.22-29:5.5": "vanishing …",
  "an11.22-29:5.6": "fading away …",
  "an11.22-29:5.7": "cessation …",
  "an11.22-29:5.8": "letting go …”"
}