{
  "_markup_path": "markup/an/an05/an5.208.html",
  "_alt_strings": [
    "en/sujato/an/an05/an5.208.json"
  ],
  "an5.208:1.1": "Aṅguttara Nikāya 5",
  "an5.208:2.1": "21. Kimilavagga",
  "an5.208:3.1": "208. Dantakaṭṭhasutta",
  "an5.208:4.1": "“Pañcime, bhikkhave, ādīnavā dantakaṭṭhassa akhādane.",
  "an5.208:4.2": "Katame pañca?",
  "an5.208:4.3": "Acakkhussaṃ, mukhaṃ duggandhaṃ hoti, rasaharaṇiyo na visujjhanti, pittaṃ semhaṃ bhattaṃ <span class=\"var\" title=\"pariyonaddhati (s1-3, km, mr) | pariyonaddhanti (pts1)\" id=\"note529\">pariyonandhati</span>, bhattamassa nacchādeti.",
  "an5.208:4.4": "Ime kho, bhikkhave, pañca ādīnavā dantakaṭṭhassa akhādane.",
  "an5.208:5.1": "Pañcime, bhikkhave, ānisaṃsā dantakaṭṭhassa khādane.",
  "an5.208:5.2": "Katame pañca?",
  "an5.208:5.3": "Cakkhussaṃ, mukhaṃ na duggandhaṃ hoti, rasaharaṇiyo visujjhanti, pittaṃ semhaṃ bhattaṃ na pariyonandhati, bhattamassa chādeti.",
  "an5.208:5.4": "Ime kho, bhikkhave, pañca ānisaṃsā dantakaṭṭhassa khādane”ti.",
  "an5.208:6.1": "Aṭṭhamaṃ."
}