{
  "_markup_path": "markup/sn/sn17/sn17.27.html",
  "_alt_strings": [
    "pi/sn/sn17/sn17.27.json"
  ],
  "sn17.27:1.1": "Linked Discourses 17 ",
  "sn17.27:2.1": "3 Third Chapter ",
  "sn17.27:3.1": "27 Ascetics and Brahmins (3)",
  "sn17.27:4.1": "At Sāvatthī. ",
  "sn17.27:4.2": "“There are ascetics and brahmins who don’t truly understand possessions, honor, and popularity, their origin, their cessation, and the path leading to their cessation …",
  "sn17.27:4.3": "There are ascetics and brahmins who do truly understand …” "
}