{
  "_markup_path": "markup/an/an06/an6.120-139.html",
  "_alt_strings": [
    "en/sujato/an/an06/an6.120-139.json"
  ],
  "an6.120-139:1.1": "Aṅguttara Nikāya 6",
  "an6.120-139:2.1": "12. Sāmaññavagga",
  "an6.120-139:3.1": "120–​139. Bhallikādisutta",
  "an6.120-139:4.1": "“Chahi, bhikkhave, dhammehi samannāgato bhalliko gahapati … pe …",
  "an6.120-139:4.2": "sudatto gahapati anāthapiṇḍiko …",
  "an6.120-139:4.3": "citto gahapati macchikāsaṇḍiko …",
  "an6.120-139:4.4": "hatthako āḷavako …",
  "an6.120-139:4.5": "mahānāmo sakko …",
  "an6.120-139:4.6": "uggo gahapati vesāliko …",
  "an6.120-139:4.7": "uggato gahapati …",
  "an6.120-139:4.8": "<span class=\\\"var\\\" title=\\\"sūro ambaṭṭho (bj, s1-3, pts1, mr)\\\" id=\\\"note290\\\">sūrambaṭṭho</span> …",
  "an6.120-139:4.9": "jīvako komārabhacco …",
  "an6.120-139:4.10": "nakulapitā gahapati …",
  "an6.120-139:4.11": "tavakaṇṇiko gahapati …",
  "an6.120-139:4.12": "pūraṇo gahapati …",
  "an6.120-139:4.13": "isidatto gahapati …",
  "an6.120-139:4.14": "<span class=\\\"var\\\" title=\\\"santāno (mr)\\\" id=\\\"note291\\\">sandhāno</span> gahapati …",
  "an6.120-139:4.15": "<span class=\\\"var\\\" title=\\\"vijayo (bj, s1-3, pts1)\\\" id=\\\"note292\\\">vicayo</span> gahapati …",
  "an6.120-139:4.16": "<span class=\\\"var\\\" title=\\\"vajjiyamahito (bj, s1-3, pts1)\\\" id=\\\"note293\\\">vijayamāhiko</span> gahapati …",
  "an6.120-139:4.17": "meṇḍako gahapati …",
  "an6.120-139:4.18": "vāseṭṭho upāsako …",
  "an6.120-139:4.19": "ariṭṭho upāsako …",
  "an6.120-139:4.20": "<span class=\\\"var\\\" title=\\\"sādatto (s1-3)\\\" id=\\\"note294\\\">sāraggo</span> upāsako tathāgate niṭṭhaṅgato amataddaso amataṃ sacchikatvā iriyati.",
  "an6.120-139:4.21": "Katamehi chahi?",
  "an6.120-139:4.22": "Buddhe aveccappasādena, dhamme aveccappasādena, saṃghe aveccappasādena, ariyena sīlena, ariyena ñāṇena, ariyāya vimuttiyā.",
  "an6.120-139:4.23": "Imehi kho, bhikkhave, chahi dhammehi samannāgato sāraggo upāsako tathāgate niṭṭhaṅgato amataddaso amataṃ sacchikatvā iriyatī”ti.",
  "an6.120-139:5.1": "Tevīsatimaṃ.",
  "an6.120-139:6.1": "Sāmaññavaggo dvādasamo."
}