{
  "_markup_path": "markup/sn/sn11/sn11.10.html",
  "_alt_strings": [
    "en/sujato/sn/sn11/sn11.10.json"
  ],
  "sn11.10:1.1": "Saṃyutta Nikāya 11",
  "sn11.10:2.1": "1. Paṭhamavagga",
  "sn11.10:3.1": "<span class=\\\"var\\\" title=\\\"isayosamuddakasuttaṃ (bj) | isayo samuddakā (sambara) (pts1)\\\" id=\\\"note533\\\">10. Samuddakasutta</span>",
  "sn11.10:4.1": "Sāvatthiyaṃ.",
  "sn11.10:4.2": "“Bhūtapubbaṃ, bhikkhave, sambahulā isayo sīlavanto kalyāṇadhammā samuddatīre paṇṇakuṭīsu sammanti.",
  "sn11.10:4.3": "Tena kho pana samayena devāsurasaṅgāmo samupabyūḷho ahosi.",
  "sn11.10:4.4": "Atha kho, bhikkhave, tesaṃ isīnaṃ sīlavantānaṃ kalyāṇadhammānaṃ etadahosi:",
  "sn11.10:4.5": "‘dhammikā kho devā, adhammikā asurā.",
  "sn11.10:4.6": "Siyāpi no asurato bhayaṃ.",
  "sn11.10:4.7": "Yannūna mayaṃ sambaraṃ asurindaṃ upasaṅkamitvā abhayadakkhiṇaṃ yāceyyāmā’ti.",
  "sn11.10:4.8": "Atha kho, bhikkhave, te isayo sīlavanto kalyāṇadhammā—",
  "sn11.10:4.9": "seyyathāpi nāma balavā puriso samiñjitaṃ vā bāhaṃ pasāreyya, pasāritaṃ vā bāhaṃ samiñjeyya;",
  "sn11.10:4.10": "evameva—",
  "sn11.10:4.11": "samuddatīre paṇṇakuṭīsu antarahitā sambarassa asurindassa sammukhe pāturahesuṃ.",
  "sn11.10:4.12": "Atha kho, bhikkhave, te isayo sīlavanto kalyāṇadhammā sambaraṃ asurindaṃ gāthāya ajjhabhāsiṃsu:",
  "sn11.10:5.1": "‘Isayo sambaraṃ pattā,",
  "sn11.10:5.2": "yācanti abhayadakkhiṇaṃ;",
  "sn11.10:5.3": "Kāmaṅkaro hi te dātuṃ,",
  "sn11.10:5.4": "bhayassa abhayassa vā’ti.",
  "sn11.10:6.1": "‘Isīnaṃ abhayaṃ natthi,",
  "sn11.10:6.2": "duṭṭhānaṃ sakkasevinaṃ;",
  "sn11.10:6.3": "Abhayaṃ yācamānānaṃ,",
  "sn11.10:6.4": "bhayameva dadāmi vo’ti.",
  "sn11.10:7.1": "‘Abhayaṃ yācamānānaṃ,",
  "sn11.10:7.2": "bhayameva dadāsi no;",
  "sn11.10:7.3": "Paṭiggaṇhāma te etaṃ,",
  "sn11.10:7.4": "akkhayaṃ hotu te bhayaṃ.",
  "sn11.10:8.1": "<span class=\\\"cross\\\" title=\\\"^ne6#466 [Sāsanapaṭṭhāna]\\\" id=\\\"note534\\\">*</span> <a class=\\\"sc\\\" id=\\\"5\\\"></a>Yādisaṃ vapate bījaṃ,",
  "sn11.10:8.2": "tādisaṃ harate phalaṃ;",
  "sn11.10:8.3": "Kalyāṇakārī kalyāṇaṃ,",
  "sn11.10:8.4": "pāpakārī ca pāpakaṃ;",
  "sn11.10:8.5": "Pavuttaṃ tāta te bījaṃ,",
  "sn11.10:8.6": "phalaṃ paccanubhossasī’ti.",
  "sn11.10:9.1": "Atha kho, bhikkhave, te isayo sīlavanto kalyāṇadhammā sambaraṃ asurindaṃ abhisapitvā—",
  "sn11.10:9.2": "seyyathāpi nāma balavā puriso samiñjitaṃ vā bāhaṃ pasāreyya, pasāritaṃ vā bāhaṃ samiñjeyya;",
  "sn11.10:9.3": "evameva—",
  "sn11.10:9.4": "sambarassa asurindassa sammukhe antarahitā samuddatīre paṇṇakuṭīsu pāturahesuṃ.",
  "sn11.10:9.5": "Atha kho, bhikkhave, sambaro asurindo tehi isīhi sīlavantehi kalyāṇadhammehi abhisapito rattiyā sudaṃ tikkhattuṃ ubbijjī”ti.",
  "sn11.10:10.1": "Paṭhamo vaggo.",
  "sn11.10:11.1": "Suvīraṃ susīmañceva,",
  "sn11.10:11.2": "dhajaggaṃ vepacittino;",
  "sn11.10:11.3": "Subhāsitaṃ jayañceva,",
  "sn11.10:11.4": "kulāvakaṃ nadubbhiyaṃ;",
  "sn11.10:11.5": "Verocana asurindo,",
  "sn11.10:11.6": "isayo araññakañceva;",
  "sn11.10:11.7": "Isayo ca samuddakāti."
}