{
  "_markup_path": "markup/sn/sn09/sn9.03.html",
  "_alt_strings": [
    "en/sujato/sn/sn09/sn9.03.json"
  ],
  "sn9.3:1.1": "Saṃyutta Nikāya 9",
  "sn9.3:2.1": "1. Vanavagga",
  "sn9.3:3.1": "3. Kassapagottasutta",
  "sn9.3:4.1": "Ekaṃ samayaṃ āyasmā kassapagotto kosalesu viharati aññatarasmiṃ vanasaṇḍe.",
  "sn9.3:4.2": "Tena kho pana samayena āyasmā kassapagotto divāvihāragato aññataraṃ chetaṃ ovadati.",
  "sn9.3:4.3": "Atha kho yā tasmiṃ vanasaṇḍe adhivatthā devatā āyasmantaṃ kassapagottaṃ saṃvejetukāmā yenāyasmā kassapagotto tenupasaṅkami;",
  "sn9.3:4.4": "upasaṅkamitvā āyasmantaṃ kassapagottaṃ gāthāhi ajjhabhāsi:",
  "sn9.3:5.1": "“Giriduggacaraṃ chetaṃ,",
  "sn9.3:5.2": "appapaññaṃ acetasaṃ;",
  "sn9.3:5.3": "Akāle ovadaṃ bhikkhu,",
  "sn9.3:5.4": "mandova paṭibhāti maṃ.",
  "sn9.3:6.1": "Suṇāti na vijānāti,",
  "sn9.3:6.2": "Āloketi na passati;",
  "sn9.3:6.3": "Dhammasmiṃ bhaññamānasmiṃ,",
  "sn9.3:6.4": "Atthaṃ bālo na bujjhati.",
  "sn9.3:7.1": "Sacepi dasa pajjote,",
  "sn9.3:7.2": "dhārayissasi kassapa;",
  "sn9.3:7.3": "Neva dakkhati rūpāni,",
  "sn9.3:7.4": "cakkhu hissa na vijjatī”ti.",
  "sn9.3:8.1": "Atha kho āyasmā kassapagotto tāya devatāya saṃvejito saṃvegamāpādīti."
}