{
  "_markup_path": "markup/an/an08/an8.005.html",
  "_alt_strings": [
    "pi/an/an08/an8.005.json"
  ],
  "an8.5:1.1": "Numbered Discourses 8 ",
  "an8.5:2.1": "1 Love ",
  "an8.5:3.1": "5 Worldly Conditions (1)",
  "an8.5:4.1": "“Mendicants, the eight worldly conditions revolve around the world, and the world revolves around the eight worldly conditions.",
  "an8.5:4.2": "What eight? ",
  "an8.5:4.3": "Gain and loss, fame and disgrace, praise and blame, pleasure and pain.",
  "an8.5:4.4": "These eight worldly conditions revolve around the world, and the world revolves around these eight worldly conditions.",
  "an8.5:5.1": "“Gain and loss, fame and disgrace,",
  "an8.5:5.2": "praise and blame, and pleasure and pain.",
  "an8.5:5.3": "These qualities among people are impermanent,",
  "an8.5:5.4": "transient, and perishable.",
  "an8.5:6.1": "A clever and mindful person knows these things, ",
  "an8.5:6.2": "seeing that they’re perishable.",
  "an8.5:6.3": "Desirable things don’t disturb their mind,",
  "an8.5:6.4": "nor are they repelled by the undesirable.",
  "an8.5:7.1": "Both favoring and opposing",
  "an8.5:7.2": "are cleared and ended, they are no more.",
  "an8.5:7.3": "Knowing the spotless, sorrowless state,",
  "an8.5:7.4": "they understand rightly, transcending rebirth.”"
}