{
  "_markup_path": "markup/an/an08/an8.031.html",
  "_alt_strings": [
    "pi/an/an08/an8.031.json"
  ],
  "an8.31:2.1": "4 Giving",
  "an8.31:3.1": "31 Giving (1)",
  "an8.31:4.1": "“Mendicants, there are these eight gifts.",
  "an8.31:4.2": "What eight? ",
  "an8.31:4.3": "A person might give a gift after insulting the recipient. Or they give out of fear. Or they give thinking, ‘They gave to me.’ Or they give thinking, ‘They’ll give to me.’ Or they give thinking, ‘It’s good to give.’ Or they give thinking, ‘I cook, they don’t. It wouldn’t be right for me to not give to them.’ ",
  "an8.31:4.4": "Or they give thinking, ‘By giving this gift I’ll get a good reputation.’ Or they give thinking, ‘This is an adornment and requisite for the mind.’",
  "an8.31:4.5": "These are the eight gifts.”"
}