{
  "_markup_path": "markup/sn/sn47/sn47.30.html",
  "_alt_strings": [
    "en/sujato/sn/sn47/sn47.30.json"
  ],
  "sn47.30:1.1": "Saṃyutta Nikāya 47",
  "sn47.30:2.1": "3. Sīlaṭṭhitivagga",
  "sn47.30:3.1": "30. Mānadinnasutta",
  "sn47.30:4.1": "Taṃyeva nidānaṃ.",
  "sn47.30:4.2": "Tena kho pana samayena mānadinno gahapati ābādhiko hoti dukkhito bāḷhagilāno.",
  "sn47.30:4.3": "Atha kho mānadinno gahapati aññataraṃ purisaṃ āmantesi:",
  "sn47.30:4.4": "“ehi tvaṃ, ambho purisa … pe …",
  "sn47.30:4.5": "na me, bhante, khamanīyaṃ na yāpanīyaṃ.",
  "sn47.30:4.6": "Bāḷhā me dukkhā vedanā abhikkamanti, no paṭikkamanti;",
  "sn47.30:4.7": "abhikkamosānaṃ paññāyati, no paṭikkamoti.",
  "sn47.30:4.8": "Evarūpāya cāhaṃ, bhante, dukkhāya vedanāya phuṭṭho samāno kāye kāyānupassī viharāmi ātāpī sampajāno satimā, vineyya loke abhijjhādomanassaṃ;",
  "sn47.30:4.9": "vedanāsu … pe …",
  "sn47.30:4.10": "citte … pe …",
  "sn47.30:4.11": "dhammesu dhammānupassī viharāmi ātāpī sampajāno satimā, vineyya loke abhijjhādomanassaṃ.",
  "sn47.30:4.12": "Yāni cimāni, bhante, bhagavatā pañcorambhāgiyāni saṃyojanāni desitāni, nāhaṃ, bhante, tesaṃ kiñci attani appahīnaṃ samanupassāmī”ti.",
  "sn47.30:4.13": "“Lābhā te, gahapati, suladdhaṃ te, gahapati.",
  "sn47.30:4.14": "Anāgāmiphalaṃ tayā, gahapati, byākatan”ti.",
  "sn47.30:5.1": "Dasamaṃ.",
  "sn47.30:6.1": "Sīlaṭṭhitivaggo tatiyo.",
  "sn47.30:7.1": "Sīlaṃ ṭhiti parihānaṃ,",
  "sn47.30:7.2": "suddhaṃ brāhmaṇapadesaṃ;",
  "sn47.30:7.3": "Samattaṃ loko sirivaḍḍho,",
  "sn47.30:7.4": "mānadinnena te dasāti."
}